retry_ops/__init__.py
retry_ops/decorators.py
tests/__init__.py
tests/test_decorators.py
retry_ops-0.2.0.dist-info/LICENSE
retry_ops-0.2.0.dist-info/METADATA
retry_ops-0.2.0.dist-info/WHEEL
retry_ops-0.2.0.dist-info/top_level.txt
retry_ops-0.2.0.dist-info/RECORD
