Metadata-Version: 2.1
Name: retry-ops
Version: 0.2.0
Summary: A Python library providing retry decorators.
Home-page: https://github.com/ChristianJaimes/retry_ops
Author: Christian Jaimes Acevedo
License: MIT
Platform: UNKNOWN
Classifier: Programming Language :: Python :: 3
Classifier: License :: OSI Approved :: MIT License
Classifier: Operating System :: OS Independent
Requires-Python: >=3.6
